selectic_py-0.1.0.dist-info/METADATA
selectic_py-0.1.0.dist-info/WHEEL
selectic_py-0.1.0.dist-info/licenses/LICENSE
selectic_py/__init__.py
selectic_py/selectic_py.cpython-312-darwin.so
selectic_py-0.1.0.dist-info/RECORD
